mnist_synthetic/.DS_Store
mnist_synthetic/__init__.py
mnist_synthetic/config.py
mnist_synthetic/generator.py
mnist_synthetic/location.py
mnist_synthetic/torch/__init__.py
mnist_synthetic/torch/datasets/__init__.py
mnist_synthetic/torch/datasets/mnist_synthetic_dataset.py
mnist_synthetic/torch/datasets/mnist_synthetic_dataset_rotated.py
mnist_synthetic/torch/transforms/to_center.py
mnist_synthetic/utils/__init__.py
mnist_synthetic/utils/drawing.py
mnist_synthetic/utils/rotation.py
mnist_synthetic-0.0.5.dist-info/METADATA
mnist_synthetic-0.0.5.dist-info/WHEEL
mnist_synthetic-0.0.5.dist-info/RECORD
