Metadata-Version: 2.4
Name: mnist_synthetic
Version: 0.0.5
Summary: 
Author: IvanHod
Author-email: Khodnenko.Ivan@gmail.com
Requires-Python: >=3.12,<3.14
Classifier: Programming Language :: Python :: 3
Classifier: Programming Language :: Python :: 3.12
Classifier: Programming Language :: Python :: 3.13
Requires-Dist: notebook (>=7.4.5,<8.0.0)
Requires-Dist: numpy (==2.2.6)
Requires-Dist: opencv-python (>=4.12.0.88,<5.0.0.0)
